[{
  "_id": {
    "$oid": "68f8aae2c1e160b04f2c5adf"
  },
  "subject": "Mathematics",
  "location": "Hendon",
  "price": 100,
  "spaces": 5,
  "icon": "fas fa-calculator",
  "image": "images/maths.jpg"
},
{
  "_id": {
    "$oid": "68f8b524c1e160b04f2c5b92"
  },
  "subject": "English Language",
  "location": "Colindale",
  "price": 90,
  "spaces": 5,
  "image": "images/english.jpg"
},
{
  "_id": {
    "$oid": "68f8b54ac1e160b04f2c5b94"
  },
  "subject": "Chemistry",
  "location": "Brent Cross",
  "price": 115,
  "spaces": 4,
  "icon": "fas fa-flask",
  "image": "images/chemistry.jpg"
},
{
  "_id": {
    "$oid": "68f8b55ec1e160b04f2c5b96"
  },
  "subject": "History",
  "location": "Golders Green",
  "price": 85,
  "spaces": 5,
  "icon": "fas fa-landmark",
  "image": "images/history.jpg"
},
{
  "_id": {
    "$oid": "68f8b574c1e160b04f2c5b9b"
  },
  "subject": "Computer Science",
  "location": "Hendon",
  "price": 125,
  "spaces": 5,
  "icon": "fas fa-laptop-code",
  "image": "images/cs.jpg"
},
{
  "_id": {
    "$oid": "68f8b587c1e160b04f2c5b9c"
  },
  "subject": "Physics",
  "location": "Mill Hill",
  "price": 110,
  "spaces": 5,
  "icon": "fas fa-atom",
  "image": "images/physics.jpg"
},
{
  "_id": {
    "$oid": "68f8b59dc1e160b04f2c5b9e"
  },
  "subject": "Art & Design",
  "location": "Colindale",
  "price": 75,
  "spaces": 4,
  "icon": "fas fa-palette",
  "image": "images/art.jpg"
},
{
  "_id": {
    "$oid": "68f8b5abc1e160b04f2c5b9f"
  },
  "subject": "Geography",
  "location": "Wembley",
  "price": 95,
  "spaces": 5,
  "icon": "fas fa-globe-europe",
  "image": "images/geo.jpg"
},
{
  "_id": {
    "$oid": "68f8b5c4c1e160b04f2c5ba1"
  },
  "subject": "Music",
  "location": "Golders Green",
  "price": 80,
  "spaces": 5,
  "icon": "fas fa-music",
  "image": "images/music.jpg"
},
{
  "_id": {
    "$oid": "68f8b5e3c1e160b04f2c5ba6"
  },
  "subject": "Biology",
  "location": "Brent Cross",
  "price": 115,
  "spaces": 4,
  "icon": "fas fa-dna",
  "image": "images/Biology.jpg"
}]